Metadata-Version: 2.1
Name: INFORMEGE
Version: 0.0.1
Summary: Will be soon
Author-email: fedor_kamushkov1234@mail.ru
License: Will be soon
